[{"_id":"1266383","_from":"97372","_to":"109201","book":7,"selection":{"text":"ἀμφιπόλοισιν"},"type":"COG.FAR"},{"_id":"1249837","_from":"99907","_to":"1249451","book":7,"selection":{"text":"τῇ δὲ Ποσειδάων ἐμίγη"},"type":"INR.NONVERBAL-NEAR/UND"},{"_id":"1264341","_from":"99653","_to":"97372","book":7,"selection":{"text":"ἐνδυκέως ἐφίλει"},"type":"INR.NONVERBAL-NEAR"},{"_id":"1249868","_from":"1123044","_to":"975898","book":7,"selection":{"text":"Ναυσίθοον μεγάθυμον, ὃς ἐν Φαίηξιν ἄνασσε·"},"type":"INR.NONVERBAL-NEAR"},{"_id":"1254728","_from":"101630","_to":"1254693","book":7,"selection":{"text":"δῶκεν Ἀθήνη111ἔργα τ’ ἐπίστασθαι περικαλλέα καὶ φρένας ἐσθλάς\\."},"type":"INR.NONVERBAL-FAR"},{"_id":"1266364","_from":"1124092","_to":"97372","book":7,"selection":{"text":"ἡ μὲν γάρ μ’ ἐκέλευε σὺν ἀμφιπόλοισιν ἕπεσθαι,"},"type":"INR.VERBAL-NEAR"},{"_id":"1266429","_from":"1123744","_to":"97372","book":7,"selection":{"text":"ξεῖν’, οὔ μοι τοιοῦτον ἐνὶ στήθεσσι φίλον κῆρ310μαψιδίως κεχολῶσθαι· ἀμείνω δ’ αἴσιμα πάντα.311αἲ γάρ, Ζεῦ τε πάτερ καὶ Ἀθηναίη καὶ Ἄπολλον,312τοῖος ἐὼν οἷός ἐσσι, τά τε φρονέων ἅ τ’ ἐγώ περ,313παῖδά τ’ ἐμὴν ἐχέμεν καὶ ἐμὸς γαμβρὸς καλέεσθαι314αὖθι μένων· οἶκον δέ κ’ ἐγὼ καὶ κτήματα δοίην,315εἴ κ’ ἐθέλων γε μένοις· ἀέκοντα δέ ς’ οὔ τις ἐρύξει316Φαιήκων· μὴ τοῦτο φίλον Διὶ πατρὶ γένοιτο.317πομπὴν δ’ ἐς τόδ’ ἐγὼ τεκμαίρομαι, ὄφρ’ ἐὺ εἰδῇς,318αὔριον ἔς· τῆμος δὲ σὺ μὲν δεδμημένος ὕπνῳ319λέξεαι, οἱ δ’ ἐλόωσι γαλήνην, ὄφρ’ ἂν ἵκηαι320πατρίδα σὴν καὶ δῶμα,  καὶ εἴ πού τοι φίλον ἐστίν,321εἴ περ καὶ μάλα πολλὸν ἑκαστέρω ἔστ’ Εὐβοίης,322τήν περ τηλοτάτω φάς’ ἔμμεναι, οἵ μιν ἴδοντο323λαῶν ἡμετέρων, ὅτε τε ξανθὸν Ῥαδάμανθυν324ἦγον ἐποψόμενον Τιτυὸν Γαιήιον υἱόν.325καὶ μὲν οἱ ἔνθ’ ἦλθον καὶ ἄτερ καμάτοιο τέλεσσαν326ἤματι τῷ αὐτῷ καὶ ἀπήνυσαν οἴκαδ’ ὀπίσσω.327εἰδήσεις δὲ καὶ αὐτὸς ἐνὶ φρεσὶν ὅσσον ἄρισται328νῆες ἐμαὶ καὶ κοῦροι ἀναρρίπτειν ἅλα πηδῷ."},"type":"INR.VERBAL-NEAR"},{"_id":"1265146","_from":"99907","_to":"97372","book":7,"selection":{"text":"τήν μοι ἐπῶρσε Ποσειδάων ἐνοσίχθων,"},"type":"INR.NONVERBAL-FAR"},{"_id":"1264388","_from":"99653","_to":"97372","book":7,"selection":{"text":" ἔφασκε257θήσειν ἀθάνατον καὶ ἀγήραον ἤματα πάντα·"},"type":"INR.VERBAL-NEAR"},{"_id":"1249371","_from":"101630","_to":"1123044","book":7,"selection":{"text":"Ναυσίθοον"},"type":"COG.FAR"},{"_id":"1255810","_from":"1255685","_to":"97372","book":7,"selection":{"text":"ξεῖνον"},"type":"INR.VERBAL-NEAR/UND"},{"_id":"1247365","_from":"101630","_to":"97372","book":7,"selection":{"text":"ἀμφὶ δ’ Ἀθήνη15πολλὴν ἠέρα χεῦε φίλα φρονέους’ Ὀδυσῆι"},"type":"INR.NONVERBAL-FAR"},{"_id":"1259002","_from":"1123744","_to":"1128411","book":7,"selection":{"text":"κέκλυτε, Φαιήκων ἡγήτορες ἠδὲ μέδοντες187ὄφρ’ εἴπω τά με θυμὸς ἐνὶ στήθεσσι κελεύει.188νῦν μὲν δαισάμενοι κατακείετε οἴκαδ’ ἰόντες·189ἠῶθεν δὲ γέροντας ἐπὶ πλέονας καλέσαντες190ξεῖνον ἐνὶ μεγάροις ξεινίσσομεν ἠδὲ θεοῖσιν191ῥέξομεν ἱερὰ καλά, ἔπειτα δὲ καὶ περὶ πομπῆς192μνησόμεθ’, ὥς χ’ ὁ ξεῖνος ἄνευθε πόνου καὶ ἀνίης193πομπῇ ὑφ’ ἡμετέρῃ ἣν πατρίδα γαῖαν ἵκηται194χαίρων καρπαλίμως, εἰ καὶ μάλα τηλόθεν ἐστί,195μηδέ τι μεσσηγύς γε κακὸν καὶ πῆμα πάθῃσι,196πρίν γε τὸν ἧς γαίης ἐπιβήμεναι· ἔνθα δ’ ἔπειτα197πείσεται, ἅσσα οἱ αἶσα κατὰ κλῶθές τε βαρεῖαι198γιγνομένῳ νήσαντο λίνῳ, ὅτε μιν τέκε μήτηρ.199εἰ δέ τις ἀθανάτων γε κατ’ οὐρανοῦ εἰλήλουθεν,200ἄλλο τι δὴ τόδ’ ἔπειτα θεοὶ περιμηχανόωνται.201αἰεὶ γὰρ τὸ πάρος γε θεοὶ φαίνονται ἐναργεῖς202ἡμῖν, εὖτ’ ἔρδωμεν ἀγακλειτὰς ἑκατόμβας,203δαίνυνταί τε παρ’ ἄμμι καθήμενοι ἔνθα περ ἡμεῖς\\.204εἰ δ’ ἄρα τις καὶ μοῦνος ἰὼν ξύμβληται ὁδίτης,205οὔ τι κατακρύπτουσιν,  ἐπεί σφισιν ἐγγύθεν εἰμέν,206ὥς περ Κύκλωπές τε καὶ ἄγρια φῦλα Γιγάντων."},"type":"INR.VERBAL-NEAR"},{"_id":"1249800","_from":"1249637","_to":"1249681","book":7,"selection":{"text":"ἀλλ’ ὁ μὲν ὤλεσε λαὸν ἀτάσθαλον"},"type":"INR.NONVERBAL-NEAR"},{"_id":"1261623","_from":"97372","_to":"671245","book":7,"selection":{"text":"δμῶάς"},"type":"COG.FAR"},{"_id":"1254709","_from":"101630","_to":"1254693","book":7,"selection":{"text":"πέρι γάρ σφισι δῶκεν Ἀθήνη111ἔργα τ’ ἐπίστασθαι περικαλλέα"},"type":"INR.NONVERBAL-FAR"},{"_id":"1266132","_from":"1124092","_to":"97372","book":7,"selection":{"text":"λοῦς’ ἐν ποταμῷ"},"type":"INR.NONVERBAL-NEAR"},{"_id":"1263010","_from":"97372","_to":"1262994","book":7,"selection":{"text":"Ἄτλαντος"},"type":"COG.FAR"},{"_id":"1256649","_from":"1123744","_to":"1256633","book":7,"selection":{"text":"Ποντόνοε, κρητῆρα κερασσάμενος μέθυ νεῖμον180πᾶσιν ἀνὰ μέγαρον,  ἵνα καὶ Διὶ τερπικεραύνῳ181σπείσομεν, ὅς θ’ ἱκέτῃσιν ἅμ’ αἰδοίοισιν ὀπηδεῖ."},"type":"INR.VERBAL-NEAR"},{"_id":"1264931","_from":"97372","_to":"100295","book":7,"selection":{"text":"Ζηνὸς"},"type":"COG.FAR"},{"_id":"1256210","_from":"1123744","_to":"97372","book":7,"selection":{"text":"ὦρσεν ἀπ’ ἐσχαρόφιν"},"type":"INR.NONVERBAL-NEAR"},{"_id":"1256409","_from":"108431","_to":"97372","book":7,"selection":{"text":"παρὰ δὲ ξεστὴν ἐτάνυσσε τράπεζαν."},"type":"INR.NONVERBAL-NEAR"},{"_id":"1264821","_from":"99653","_to":"97372","book":7,"selection":{"text":"μ’ ἐκέλευσεν ἐποτρύνουσα νέεσθαι"},"type":"INR.VERBAL-NEAR"},{"_id":"1255471","_from":"97372","_to":"99765","book":7,"selection":{"text":"θεοὶ"},"type":"COG.FAR"},{"_id":"1266336","_from":"97372","_to":"1124092","book":7,"selection":{"text":"ἀμύμονα νείκεε κούρην"},"type":"COG.FAR"},{"_id":"1259765","_from":"1123744","_to":"1259749","book":7,"selection":{"text":"κλῶθές"},"type":"COG.FAR"},{"_id":"1256280","_from":"1123744","_to":"1256255","book":7,"selection":{"text":"υἱὸν ἀναστήσας ἀγαπήνορα Λαοδάμαντα"},"type":"INR.VERBAL-NEAR"},{"_id":"1255434","_from":"97372","_to":"1123744","book":7,"selection":{"text":"σόν τε πόσιν"},"type":"INR.VERBAL-NEAR/UND"},{"_id":"1250067","_from":"101630","_to":"1123744","book":7,"selection":{"text":"Ἀλκίνοόν"},"type":"COG.FAR"},{"_id":"1259642","_from":"1123744","_to":"99765","book":7,"selection":{"text":"θεοῖσιν"},"type":"COG.FAR"},{"_id":"1255984","_from":"1255685","_to":"100295","book":7,"selection":{"text":"Διὶ"},"type":"COG.FAR"},{"_id":"1253329","_from":"101630","_to":"1253304","book":7,"selection":{"text":"δῦνε δ’ Ἐρεχθῆος πυκινὸν δόμον"},"type":"INR.NONVERBAL-NEAR/UND"},{"_id":"1250516","_from":"101630","_to":"975898","book":7,"selection":{"text":"λαῶν"},"type":"COG.FAR"},{"_id":"1250296","_from":"1123744","_to":"1125369","book":7,"selection":{"text":" ὡς οὔ τις ἐπὶ χθονὶ τίεται ἄλλη,"},"type":"COG.NEAR"},{"_id":"1267682","_from":"1123744","_to":"109241","book":7,"selection":{"text":"ἐμαὶ καὶ κοῦροι"},"type":"COG.FAR"},{"_id":"1249346","_from":"101630","_to":"1123744","book":7,"selection":{"text":" Ἀλκίνοον βασιλῆα."},"type":"COG.FAR"},{"_id":"1261759","_from":"1128411","_to":"97372","book":7,"selection":{"text":"οἱ δ’ ἄρα πάντες ἐπῄνεον"},"type":"INR.VERBAL-NEAR"},{"_id":"1265053","_from":"97372","_to":"99653","book":7,"selection":{"text":" προέηκεν"},"type":"COG.FAR"},{"_id":"1255847","_from":"1255685","_to":"1128411","book":7,"selection":{"text":"οἵδε δὲ σὸν μῦθον ποτιδέγμενοι ἰσχανόωνται"},"type":"INR.VERBAL-NEAR/UND"},{"_id":"1248596","_from":"101630","_to":"97372","book":7,"selection":{"text":"τοιγὰρ ἐγώ τοι, ξεῖνε πάτερ, δόμον, ὅν με κελεύεις,29δείξω, ἐπεί μοι πατρὸς ἀμύμονος ἐγγύθι ναίει.30ἀλλ’ ἴθι σιγῇ τοῖον,  ἐγὼ δ’ ὁδὸν ἡγεμονεύσω,31μηδέ τιν’ ἀνθρώπων προτιόσσεο μηδ’ ἐρέεινε.32οὐ γὰρ ξείνους οἵδε μάλ’ ἀνθρώπους ἀνέχονται,33οὐδ’ ἀγαπαζόμενοι φιλέους’ ὅς κ’ ἄλλοθεν ἔλθῃ.34νηυσὶ θοῇσιν τοί γε πεποιθότες ὠκείῃσι35λαῖτμα μέγ’ ἐκπερόωσιν,  ἐπεί σφισι δῶκ’ ἐνοσίχθων·36τῶν νέες ὠκεῖαι ὡς εἰ πτερὸν ἠὲ νόημα."},"type":"INR.VERBAL-NEAR"},{"_id":"1254261","_from":"645196","_to":"1128411","book":7,"selection":{"text":"αἱ μὲν ἀλετρεύουσι μύλῃς ἔπι μήλοπα καρπόν"},"type":"INR.NONVERBAL-NEAR"},{"_id":"1248990","_from":"101630","_to":"97372","book":7,"selection":{"text":"ἡγήσατο Παλλὰς Ἀθήνη38καρπαλίμως"},"type":"INR.NONVERBAL-NEAR"},{"_id":"1262325","_from":"1125369","_to":"109201","book":7,"selection":{"text":"  τά ῥ’ αὐτὴ τεῦξε σὺν ἀμφιπόλοισι γυναιξί·"},"type":"COG.FAR"},{"_id":"1250144","_from":"101630","_to":"569640","book":7,"selection":{"text":"ἀργυρότοξος Ἀπόλλων65"},"type":"COG.FAR"},{"_id":"1267902","_from":"109201","_to":"97372","book":7,"selection":{"text":"στόρεσαν πυκινὸν λέχος ἐγκονέουσαι,"},"type":"INR.NONVERBAL-NEAR"},{"_id":"1249716","_from":"1249637","_to":"1249681","book":7,"selection":{"text":"ὑπερθύμοισι Γιγάντεσσιν βασίλευεν."},"type":"INR.NONVERBAL-NEAR"},{"_id":"1256749","_from":"1123744","_to":"100295","book":7,"selection":{"text":"Διὶ"},"type":"COG.FAR"},{"_id":"1249284","_from":"101630","_to":"110110","book":7,"selection":{"text":"ἀνὴρ"},"type":"COG.FAR"},{"_id":"1248953","_from":"101630","_to":"99907","book":7,"selection":{"text":"ἐνοσίχθων"},"type":"COG.FAR"},{"_id":"1264996","_from":"99653","_to":"97372","book":7,"selection":{"text":"ἄμβροτα εἵματα ἕσσεν,"},"type":"INR.NONVERBAL-NEAR"},{"_id":"1262959","_from":"99765","_to":"97372","book":7,"selection":{"text":" μοι πολλὰ δόσαν θεοὶ Οὐρανίωνες·"},"type":"INR.NONVERBAL-FAR"},{"_id":"1250086","_from":"1123044","_to":"1250023","book":7,"selection":{"text":"Ναυσίθοος δ’ ἔτεκεν Ῥηξήνορά"},"type":"INR.NONVERBAL-NEAR"},{"_id":"1261496","_from":"97372","_to":"100958","book":7,"selection":{"text":"βροτοῖσιν"},"type":"COG.FAR"},{"_id":"1267608","_from":"1123744","_to":"1267601","book":7,"selection":{"text":"Τιτυὸν"},"type":"COG.FAR"},{"_id":"1266188","_from":"1123744","_to":"97372","book":7,"selection":{"text":"ξεῖν’, ἦ τοι μὲν τοῦτο γ’ ἐναίσιμον οὐκ ἐνόησε300παῖς ἐμή,  οὕνεκά ς’ οὔ τι μετ’ ἀμφιπόλοισι γυναιξὶν301ἦγεν ἐς ἡμέτερον, σὺ δ’ ἄρα πρώτην ἱκέτευσας\\."},"type":"INR.VERBAL-NEAR"},{"_id":"1248843","_from":"101630","_to":"110110","book":7,"selection":{"text":"μοι πατρὸς ἀμύμονος"},"type":"COG.FAR"},{"_id":"1249256","_from":"101630","_to":"1128411","book":7,"selection":{"text":"διοτρεφέας βασιλῆας"},"type":"COG.FAR"},{"_id":"1256593","_from":"641429","_to":"94990","book":7,"selection":{"text":"εἴδατα πόλλ’ ἐπιθεῖσα"},"type":"INR.NONVERBAL-NEAR"},{"_id":"1249735","_from":"99907","_to":"1123044","book":7,"selection":{"text":"Ναυσίθοον μὲν πρῶτα Ποσειδάων ἐνοσίχθων57γείνατο καὶ Περίβοια"},"type":"INR.NONVERBAL-NEAR"},{"_id":"1265610","_from":"97372","_to":"544795","book":7,"selection":{"text":"θεὸς"},"type":"COG.FAR"},{"_id":"1255059","_from":"1128411","_to":"101200","book":7,"selection":{"text":"Φαιήκων ἡγήτορας ἠδὲ μέδοντας137σπένδοντας δεπάεσσιν ἐυσκόπῳ ἀργεϊφόντῃ"},"type":"INR.NONVERBAL-FAR"},{"_id":"1267125","_from":"1123744","_to":"569640","book":7,"selection":{"text":"Ἄπολλον"},"type":"COG.FAR"},{"_id":"1250692","_from":"1125369","_to":"110110","book":7,"selection":{"text":"ᾗσι τ’ ἐὺ φρονέῃσι καὶ ἀνδράσι νείκεα λύει"},"type":"INR.NONVERBAL-NEAR"},{"_id":"1256768","_from":"1123744","_to":"1128411","book":7,"selection":{"text":"πᾶσιν ἀνὰ μέγαρον"},"type":"COG.FAR"},{"_id":"1249327","_from":"101630","_to":"1125369","book":7,"selection":{"text":"δέσποιναν μὲν πρῶτα κιχήσεαι ἐν μεγάροισιν·54Ἀρήτη"},"type":"COG.FAR"},{"_id":"1262940","_from":"97372","_to":"99765","book":7,"selection":{"text":"θεοὶ Οὐρανίωνες"},"type":"COG.FAR"},{"_id":"1247293","_from":"1246129","_to":"1124092","book":7,"selection":{"text":"ἣ τρέφε Ναυσικάαν λευκώλενον ἐν μεγάροισιν"},"type":"INR.NONVERBAL-NEAR"},{"_id":"1263029","_from":"97372","_to":"99653","book":7,"selection":{"text":"δολόεσσα Καλυψὼ"},"type":"COG.FAR"},{"_id":"1265861","_from":"97372","_to":"1265845","book":7,"selection":{"text":"θεῇσι"},"type":"COG.FAR"},{"_id":"1259506","_from":"1123744","_to":"97372","book":7,"selection":{"text":"ξεῖνον"},"type":"INR.VERBAL-NEAR/UND"},{"_id":"1256399","_from":"108431","_to":"97372","book":7,"selection":{"text":"χέρνιβα δ’ ἀμφίπολος προχόῳ ἐπέχευε φέρουσα173καλῇ χρυσείῃ ὑπὲρ ἀργυρέοιο λέβητος,174νίψασθαι·"},"type":"INR.NONVERBAL-NEAR"},{"_id":"1264068","_from":"97372","_to":"100295","book":7,"selection":{"text":"Ζεὺς"},"type":"COG.FAR"},{"_id":"1250203","_from":"569640","_to":"1250023","book":7,"selection":{"text":"τὸν μὲν ἄκουρον ἐόντα βάλ’ ἀργυρότοξος Ἀπόλλων65νυμφίον ἐν μεγάρῳ"},"type":"INR.NONVERBAL-FAR"},{"_id":"1249754","_from":"1249451","_to":"1123044","book":7,"selection":{"text":"Ναυσίθοον μὲν πρῶτα Ποσειδάων ἐνοσίχθων57γείνατο καὶ Περίβοια"},"type":"INR.NONVERBAL-NEAR"},{"_id":"1262121","_from":"1123744","_to":"97372","book":7,"selection":{"text":"πὰρ δέ οἱ Ἀρήτη τε καὶ Ἀλκίνοος θεοειδὴς"},"type":"INR.NONVERBAL-NEAR/UND"},{"_id":"1250479","_from":"101630","_to":"1123744","book":7,"selection":{"text":"Ἀλκινόοιο"},"type":"COG.FAR"},{"_id":"1249082","_from":"101630","_to":"97372","book":7,"selection":{"text":"φίλα φρονέους’ ἐνὶ θυμῷ."},"type":"COG.NEAR"},{"_id":"1264449","_from":"99653","_to":"97372","book":7,"selection":{"text":"ἔτρεφεν"},"type":"INR.NONVERBAL-NEAR"},{"_id":"1256048","_from":"100295","_to":"161301","book":7,"selection":{"text":"ὅς θ’ ἱκέτῃσιν ἅμ’ αἰδοίοισιν ὀπηδεῖ·"},"type":"INR.NONVERBAL-FAR"},{"_id":"1263660","_from":"100295","_to":"97372","book":7,"selection":{"text":"μοι νῆα θοὴν ἀργῆτι κεραυνῷ250Ζεὺς ἔλσας ἐκέασσε μέσῳ ἐνὶ οἴνοπι πόντῳ."},"type":"INR.NONVERBAL-FAR"},{"_id":"1264784","_from":"99653","_to":"97372","book":7,"selection":{"text":"τά μοι ἄμβροτα δῶκε Καλυψώ·"},"type":"INR.NONVERBAL-NEAR"},{"_id":"1260780","_from":"1123744","_to":"99765","book":7,"selection":{"text":"σφισιν"},"type":"COG.FAR"},{"_id":"1264858","_from":"99653","_to":"97372","book":7,"selection":{"text":"μ’ ἐκέλευσεν ἐποτρύνουσα νέεσθαι"},"type":"INR.NONVERBAL-NEAR"},{"_id":"1262240","_from":"109201","_to":"1123744","book":7,"selection":{"text":"ἀμφίπολοι δ’ ἀπεκόσμεον ἔντεα δαιτός\\."},"type":"INR.NONVERBAL-NEAR"},{"_id":"1267496","_from":"1123744","_to":"875656","book":7,"selection":{"text":"ξανθὸν Ῥαδάμανθυν"},"type":"COG.FAR"},{"_id":"1255559","_from":"97372","_to":"1255543","book":7,"selection":{"text":"παισὶν"},"type":"COG.FAR"},{"_id":"1264237","_from":"97372","_to":"99765","book":7,"selection":{"text":"θεοί"},"type":"COG.FAR"},{"_id":"1254819","_from":"864072","_to":"975898","book":7,"selection":{"text":"Ζεφυρίη πνείουσα τὰ μὲν φύει,"},"type":"INR.NONVERBAL-NEAR"},{"_id":"1247338","_from":"1246129","_to":"1124092","book":7,"selection":{"text":"εἴσω δόρπον ἐκόσμει."},"type":"COG.FAR"},{"_id":"1265773","_from":"97372","_to":"109201","book":7,"selection":{"text":"ἀμφιπόλους"},"type":"COG.FAR"},{"_id":"1267533","_from":"975898","_to":"875656","book":7,"selection":{"text":"ξανθὸν Ῥαδάμανθυν324ἦγον"},"type":"INR.NONVERBAL-NEAR"},{"_id":"1262315","_from":"1125369","_to":"97372","book":7,"selection":{"text":"χιτῶνά τε εἵματ’ ἰδοῦσα235καλά"},"type":"COG.FAR"},{"_id":"1253593","_from":"1036466","_to":"1123744","book":7,"selection":{"text":"ἔργα γυναικῶν"},"type":"INR.NONVERBAL-NEAR"},{"_id":"1266216","_from":"1123744","_to":"1124092","book":7,"selection":{"text":"παῖς ἐμή"},"type":"COG.FAR"},{"_id":"1259111","_from":"1123744","_to":"975898","book":7,"selection":{"text":"Φαιήκων"},"type":"COG.FAR"},{"_id":"1250222","_from":"101630","_to":"1125369","book":7,"selection":{"text":"Ἀρήτην"},"type":"COG.FAR"},{"_id":"1262221","_from":"109201","_to":"97372","book":7,"selection":{"text":"ἀμφίπολοι δ’ ἀπεκόσμεον ἔντεα δαιτός\\."},"type":"INR.NONVERBAL-NEAR"},{"_id":"1255499","_from":"97372","_to":"1128411","book":7,"selection":{"text":"τούσδε τε δαιτυμόνας"},"type":"INR.VERBAL-NEAR/UND"},{"_id":"1250277","_from":"1123744","_to":"1125369","book":7,"selection":{"text":"καί μιν ἔτις’"},"type":"INR.NONVERBAL-NEAR"},{"_id":"1265127","_from":"97372","_to":"99907","book":7,"selection":{"text":"Ποσειδάων ἐνοσίχθων,"},"type":"COG.FAR"},{"_id":"1265081","_from":"99653","_to":"97372","book":7,"selection":{"text":"οὖρον δὲ προέηκεν ἀπήμονά τε λιαρόν τε."},"type":"INR.NONVERBAL-NEAR"},{"_id":"1248550","_from":"97372","_to":"975898","book":7,"selection":{"text":"τοῖσδε μετ’ ἀνθρώποισι"},"type":"COG.FAR"},{"_id":"1246060","_from":"1245828","_to":"1124092","book":7,"selection":{"text":"ἡμιόνους ἔλυον"},"type":"INR.NONVERBAL-NEAR"},{"_id":"1249653","_from":"101630","_to":"1249637","book":7,"selection":{"text":"μεγαλήτορος Εὐρυμέδοντος,"},"type":"COG.FAR"},{"_id":"1264977","_from":"99653","_to":"97372","book":7,"selection":{"text":" πολλὰ δ’ ἔδωκε,265σῖτον καὶ μέθυ ἡδύ"},"type":"INR.NONVERBAL-NEAR"},{"_id":"1255231","_from":"97372","_to":"1125369","book":7,"selection":{"text":"ἀμφὶ δ’ ἄρ’ Ἀρήτης βάλε γούνασι χεῖρας Ὀδυσσεύς,"},"type":"INR.NONVERBAL-NEAR"},{"_id":"1261796","_from":"1128411","_to":"97372","book":7,"selection":{"text":"κέλευον227πεμπέμεναι τὸν ξεῖνον, ἐπεὶ κατὰ μοῖραν ἔειπεν."},"type":"INR.VERBAL-NEAR"},{"_id":"1250563","_from":"975898","_to":"1125369","book":7,"selection":{"text":"οἵ μίν ῥα θεὸν ὣς εἰσορόωντες72"},"type":"COG.NEAR"},{"_id":"1266076","_from":"97372","_to":"1124092","book":7,"selection":{"text":"τὴν ἱκέτευς’"},"type":"INR.VERBAL-NEAR"},{"_id":"1249119","_from":"97372","_to":"106091","book":7,"selection":{"text":"ἡρώων"},"type":"COG.PCR"},{"_id":"1255406","_from":"97372","_to":"1250023","book":7,"selection":{"text":"Ῥηξήνορος"},"type":"COG.FAR"},{"_id":"1260855","_from":"97372","_to":"1123744","book":7,"selection":{"text":"Ἀλκίνο’, ἄλλο τί τοι μελέτω φρεσίν· οὐ γὰρ ἐγώ γε209ἀθανάτοισιν ἔοικα, τοὶ οὐρανὸν εὐρὺν ἔχουσιν,210οὐ δέμας οὐδὲ φυήν,  ἀλλὰ θνητοῖσι βροτοῖσιν.211οὕς τινας ὑμεῖς ἴστε μάλιστ’ ὀχέοντας ὀιζὺν212ἀνθρώπων, τοῖσίν κεν ἐν ἄλγεσιν ἰσωσαίμην.213καὶ δ’ ἔτι κεν καὶ μᾶλλον ἐγὼ κακὰ μυθησαίμην,214ὅσσα γε δὴ ξύμπαντα θεῶν ἰότητι μόγησα.215ἀλλ’ ἐμὲ μὲν δορπῆσαι ἐάσατε κηδόμενόν περ·216οὐ γάρ τι στυγερῇ ἐπὶ γαστέρι κύντερον ἄλλο217ἔπλετο, ἥ τ’ ἐκέλευσεν ἕο μνήσασθαι ἀνάγκῃ218καὶ μάλα τειρόμενον καὶ ἐνὶ φρεσὶ πένθος ἔχοντα,219ὡς καὶ ἐγὼ πένθος μὲν ἔχω φρεσίν, ἡ δὲ μάλ’ αἰεὶ220ἐσθέμεναι κέλεται καὶ πινέμεν,  ἐκ δέ με πάντων221ληθάνει ὅσς’ ἔπαθον, καὶ ἐνιπλησθῆναι ἀνώγει.222ὑμεῖς δ’ ὀτρύνεσθαι ἅμ’ ἠοῖ φαινομένηφιν,223ὥς κ’ ἐμὲ τὸν δύστηνον ἐμῆς ἐπιβήσετε πάτρης224καί περ πολλὰ παθόντα· ἰδόντα με καὶ λίποι αἰὼν225κτῆσιν ἐμήν, δμῶάς τε καὶ ὑψερεφὲς μέγα δῶμα."},"type":"INR.VERBAL-NEAR"},{"_id":"1265591","_from":"544795","_to":"97372","book":7,"selection":{"text":"ὕπνον δὲ θεὸς κατ’ ἀπείρονα χεῦεν."},"type":"INR.NONVERBAL-FAR"},{"_id":"1263550","_from":"97372","_to":"100958","book":7,"selection":{"text":"θνητῶν ἀνθρώπων."},"type":"COG.FAR"},{"_id":"1265563","_from":"97372","_to":"1040438","book":7,"selection":{"text":"διιπετέος ποταμοῖο"},"type":"COG.FAR"},{"_id":"1250646","_from":"101630","_to":"1125369","book":7,"selection":{"text":"αὐτὴ"},"type":"COG.FAR"},{"_id":"1249063","_from":"101630","_to":"97372","book":7,"selection":{"text":"ἥ ῥά οἱ ἀχλὺν42θεσπεσίην κατέχευε"},"type":"INR.NONVERBAL-NEAR"},{"_id":"1267949","_from":"109201","_to":"97372","book":7,"selection":{"text":"ὄρσο κέων, ὦ ξεῖνε· πεποίηται δέ τοι εὐνή."},"type":"INR.VERBAL-NEAR"},{"_id":"1250365","_from":"101630","_to":"1250358","book":7,"selection":{"text":"φίλων παίδων"},"type":"COG.NEAR"},{"_id":"1250039","_from":"101630","_to":"1250023","book":7,"selection":{"text":"Ναυσίθοος δ’ ἔτεκεν Ῥηξήνορά"},"type":"COG.FAR"},{"_id":"1267636","_from":"875656","_to":"1267601","book":7,"selection":{"text":"Ῥαδάμανθυν324ἦγον ἐποψόμενον Τιτυὸν"},"type":"INR.NONVERBAL-NEAR/UND"},{"_id":"1260384","_from":"99765","_to":"975898","book":7,"selection":{"text":"δαίνυνταί τε παρ’ ἄμμι καθήμενοι ἔνθα περ ἡμεῖς\\."},"type":"INR.NONVERBAL-NEAR/UND"},{"_id":"1267921","_from":"109201","_to":"97372","book":7,"selection":{"text":"ὤτρυνον δ’ Ὀδυσῆα"},"type":"INR.NONVERBAL-NEAR/UND"},{"_id":"1249915","_from":"101630","_to":"1123044","book":7,"selection":{"text":"Ναυσίθοον"},"type":"COG.FAR"},{"_id":"1246919","_from":"975898","_to":"1123744","book":7,"selection":{"text":"θεοῦ δ’ ὣς δῆμος ἄκουεν"},"type":"COG.FAR"},{"_id":"1249896","_from":"101630","_to":"975898","book":7,"selection":{"text":"Φαίηξιν"},"type":"COG.FAR"},{"_id":"1256229","_from":"1123744","_to":"97372","book":7,"selection":{"text":"ἐπὶ θρόνου εἷσε φαεινοῦ,"},"type":"INR.NONVERBAL-NEAR"},{"_id":"1247320","_from":"1246129","_to":"1124092","book":7,"selection":{"text":"ἥ οἱ πῦρ ἀνέκαιε"},"type":"COG.FAR"},{"_id":"1256118","_from":"1253304","_to":"641429","book":7,"selection":{"text":"δόρπον δὲ ξείνῳ ταμίη δότω ἔνδον ἐόντων"},"type":"INR.VERBAL-NEAR/UND"},{"_id":"1245853","_from":"1245828","_to":"1124092","book":7,"selection":{"text":"κασίγνητοι δέ μιν ἀμφὶς5ἵσταντ’"},"type":"INR.NONVERBAL-NEAR/UND"},{"_id":"1267865","_from":"1125369","_to":"109201","book":7,"selection":{"text":"κέκλετο δ’ Ἀρήτη λευκώλενος ἀμφιπόλοισιν336δέμνῐ ὑπ’ αἰθούσῃ θέμεναι καὶ ῥήγεα καλὰ337πορφύρε’ ἐμβαλέειν, στορέσαι τ’ ἐφύπερθε τάπητας338χλαίνας τ’ ἐνθέμεναι οὔλας καθύπερθεν ἕσασθαι."},"type":"INR.VERBAL-NEAR"},{"_id":"1255166","_from":"97372","_to":"1125369","book":7,"selection":{"text":"ὄφρ’ ἵκετ’ Ἀρήτην"},"type":"INR.NONVERBAL-NEAR/UND"},{"_id":"1255902","_from":"1255685","_to":"109134","book":7,"selection":{"text":"κηρύκεσσι"},"type":"INR.VERBAL-NEAR/UND"},{"_id":"1248898","_from":"101630","_to":"110110","book":7,"selection":{"text":"τιν’ ἀνθρώπων"},"type":"COG.FAR"},{"_id":"1262250","_from":"109201","_to":"1125369","book":7,"selection":{"text":"ἀμφίπολοι δ’ ἀπεκόσμεον ἔντεα δαιτός\\."},"type":"INR.NONVERBAL-NEAR"},{"_id":"1267566","_from":"1123744","_to":"1267550","book":7,"selection":{"text":"Γαιήιον"},"type":"COG.FAR"},{"_id":"1246069","_from":"1245828","_to":"1124092","book":7,"selection":{"text":"ἐσθῆτά τε ἔσφερον εἴσω."},"type":"INR.NONVERBAL-NEAR"},{"_id":"1262074","_from":"1128411","_to":"99765","book":7,"selection":{"text":"αὐτὰρ ἐπεὶ σπεῖσάν τ’ ἔπιον"},"type":"INR.NONVERBAL-FAR"},{"_id":"1260818","_from":"1123744","_to":"1249681","book":7,"selection":{"text":"Γιγάντων"},"type":"COG.FAR"},{"_id":"1253801","_from":"109241","_to":"1128411","book":7,"selection":{"text":"χρύσειοι δ’ ἄρα κοῦροι ἐυδμήτων ἐπὶ βωμῶν101ἕστασαν αἰθομένας δαΐδας μετὰ χερσὶν ἔχοντες"},"type":"INR.NONVERBAL-NEAR"},{"_id":"1262840","_from":"97372","_to":"1125369","book":7,"selection":{"text":"ἀργαλέον,  βασίλεια, διηνεκέως ἀγορεῦσαι242κήδε’, ἐπεί μοι πολλὰ δόσαν θεοὶ Οὐρανίωνες·243τοῦτο δέ τοι ἐρέω ὅ μ’ ἀνείρεαι ἠδὲ μεταλλᾷς\\.244Ὠγυγίη τις νῆσος ἀπόπροθεν εἰν ἁλὶ κεῖται·245ἔνθα μὲν Ἄτλαντος θυγάτηρ,  δολόεσσα Καλυψὼ246ναίει ἐυπλόκαμος, δεινὴ θεός· οὐδέ τις αὐτῇ247μίσγεται οὔτε θεῶν οὔτε θνητῶν ἀνθρώπων.248ἀλλ’ ἐμὲ τὸν δύστηνον ἐφέστιον ἤγαγε δαίμων249οἶον, ἐπεί μοι νῆα θοὴν ἀργῆτι κεραυνῷ250Ζεὺς ἔλσας ἐκέασσε μέσῳ ἐνὶ οἴνοπι πόντῳ.251ἔνθ’ ἄλλοι μὲν πάντες ἀπέφθιθεν ἐσθλοὶ ἑταῖροι,252αὐτὰρ ἐγὼ τρόπιν ἀγκὰς ἑλὼν νεὸς ἀμφιελίσσης253ἐννῆμαρ φερόμην· δεκάτῃ δέ με νυκτὶ μελαίνῃ254νῆσον ἐς Ὠγυγίην πέλασαν θεοί, ἔνθα Καλυψὼ255ναίει ἐυπλόκαμος,  δεινὴ θεός, ἥ με λαβοῦσα256ἐνδυκέως ἐφίλει τε καὶ ἔτρεφεν ἠδὲ ἔφασκε257θήσειν ἀθάνατον καὶ ἀγήραον ἤματα πάντα·258ἀλλ’ ἐμὸν οὔ ποτε θυμὸν ἐνὶ στήθεσσιν ἔπειθεν.259ἔνθα μὲν ἑπτάετες μένον ἔμπεδον, εἵματα δ’ αἰεὶ260δάκρυσι δεύεσκον,  τά μοι ἄμβροτα δῶκε Καλυψώ·261ἀλλ’ ὅτε δὴ ὀγδόατόν μοι ἐπιπλόμενον ἔτος ἦλθεν,262καὶ τότε δή μ’ ἐκέλευσεν ἐποτρύνουσα νέεσθαι263Ζηνὸς ὑπ’ ἀγγελίης, ἢ καὶ νόος ἐτράπετ’ αὐτῆς\\.264πέμπε δ’ ἐπὶ σχεδίης πολυδέσμου, πολλὰ δ’ ἔδωκε,265σῖτον καὶ μέθυ ἡδύ,  καὶ ἄμβροτα εἵματα ἕσσεν,266οὖρον δὲ προέηκεν ἀπήμονά τε λιαρόν τε.267ἑπτὰ δὲ καὶ δέκα μὲν πλέον ἤματα ποντοπορεύων,268ὀκτωκαιδεκάτῃ δ’ ἐφάνη ὄρεα σκιόεντα269γαίης ὑμετέρης, γήθησε δέ μοι φίλον ἦτορ270δυσμόρῳ· ἦ γὰρ ἔμελλον ἔτι ξυνέσεσθαι ὀιζυῖ271πολλῇ, τήν μοι ἐπῶρσε Ποσειδάων ἐνοσίχθων,272ὅς μοι ἐφορμήσας ἀνέμους κατέδησε κέλευθον,273ὤρινεν δὲ θάλασσαν ἀθέσφατον, οὐδέ τι κῦμα274εἴα ἐπὶ σχεδίης ἁδινὰ στενάχοντα φέρεσθαι.275τὴν μὲν ἔπειτα θύελλα διεσκέδας’· αὐτὰρ ἐγώ γε276νηχόμενος τόδε λαῖτμα διέτμαγον, ὄφρα με γαίῃ277ὑμετέρῃ ἐπέλασσε φέρων ἄνεμός τε καὶ ὕδωρ.278ἔνθα κέ μ’ ἐκβαίνοντα βιήσατο κῦμ’ ἐπὶ χέρσου,279πέτρῃς πρὸς μεγάλῃσι βαλὸν καὶ ἀτερπέι χώρῳ·280ἀλλ’ ἀναχασσάμενος νῆχον πάλιν,  ἧος ἐπῆλθον281ἐς ποταμόν, τῇ δή μοι ἐείσατο χῶρος ἄριστος,282λεῖος πετράων, καὶ ἐπὶ σκέπας ἦν ἀνέμοιο.283ἐκ δ’ ἔπεσον θυμηγερέων, ἐπὶ δ’ ἀμβροσίη νὺξ284ἤλυθ’. ἐγὼ δ’ ἀπάνευθε διιπετέος ποταμοῖο285ἐκβὰς ἐν θάμνοισι κατέδραθον,  ἀμφὶ δὲ φύλλα286ἠφυσάμην· ὕπνον δὲ θεὸς κατ’ ἀπείρονα χεῦεν.287ἔνθα μὲν ἐν φύλλοισι φίλον τετιημένος ἦτορ288εὗδον παννύχιος καὶ ἐπ’ ἠῶ καὶ μέσον ἦμαρ.289δείλετό τ’ ἠέλιος καί με γλυκὺς ὕπνος ἀνῆκεν.290ἀμφιπόλους δ’ ἐπὶ θινὶ τεῆς ἐνόησα θυγατρὸς291παιζούσας, ἐν δ’ αὐτὴ ἔην ἐικυῖα θεῇσι·292τὴν ἱκέτευς’· ἡ δ’ οὔ τι νοήματος ἤμβροτεν ἐσθλοῦ,293ὡς οὐκ ἂν ἔλποιο νεώτερον ἀντιάσαντα294ἐρξέμεν· αἰεὶ γάρ τε νεώτεροι ἀφραδέουσιν.295ἥ μοι σῖτον ἔδωκεν ἅλις ἠδ’ αἴθοπα οἶνον296καὶ λοῦς’ ἐν ποταμῷ καί μοι τάδε εἵματ’ ἔδωκε.297ταῦτά τοι ἀχνύμενός περ ἀληθείην κατέλεξα."},"type":"INR.VERBAL-NEAR"},{"_id":"1267810","_from":"97372","_to":"1123744","book":7,"selection":{"text":"Ἀλκίνοος"},"type":"INR.VERBAL-NEAR/UND"},{"_id":"1260354","_from":"975898","_to":"99765","book":7,"selection":{"text":"εὖτ’ ἔρδωμεν ἀγακλειτὰς ἑκατόμβας"},"type":"INR.NONVERBAL-FAR"},{"_id":"1263632","_from":"1259749","_to":"97372","book":7,"selection":{"text":"ἐμὲ τὸν δύστηνον ἐφέστιον ἤγαγε δαίμων249οἶον"},"type":"INR.NONVERBAL-FAR"},{"_id":"1267087","_from":"1123744","_to":"100295","book":7,"selection":{"text":" Ζεῦ τε πάτερ"},"type":"COG.FAR"},{"_id":"1262478","_from":"1125369","_to":"97372","book":7,"selection":{"text":"ξεῖνε, τὸ μέν σε πρῶτον ἐγὼν εἰρήσομαι αὐτή·238τίς πόθεν εἰς ἀνδρῶν; τίς τοι τάδε εἵματ’ ἔδωκεν;239οὐ δὴ φῆς ἐπὶ πόντον ἀλώμενος ἐνθάδ’ ἱκέσθαι;"},"type":"INR.VERBAL-NEAR"},{"_id":"1249381","_from":"101630","_to":"99907","book":7,"selection":{"text":"Ποσειδάων ἐνοσίχθων"},"type":"COG.FAR"},{"_id":"1249467","_from":"101630","_to":"1249451","book":7,"selection":{"text":"Περίβοια, γυναικῶν εἶδος ἀρίστη,"},"type":"COG.FAR"},{"_id":"1267199","_from":"1123744","_to":"975898","book":7,"selection":{"text":"Φαιήκων"},"type":"COG.FAR"},{"_id":"1246883","_from":"161301","_to":"1246129","book":7,"selection":{"text":"αὐτὴν γέρας ἔξελον"},"type":"INR.NONVERBAL-NEAR"},{"_id":"1264765","_from":"97372","_to":"99653","book":7,"selection":{"text":"Καλυψώ"},"type":"COG.FAR"},{"_id":"1264030","_from":"97372","_to":"98206","book":7,"selection":{"text":"πάντες ἀπέφθιθεν ἐσθλοὶ ἑταῖροι,"},"type":"COG.FAR"},{"_id":"1255147","_from":"101630","_to":"97372","book":7,"selection":{"text":"ἥν οἱ περίχευεν Ἀθήνη"},"type":"INR.NONVERBAL-FAR"},{"_id":"1262749","_from":"1125369","_to":"100958","book":7,"selection":{"text":"ἀνδρῶν"},"type":"COG.FAR"},{"_id":"1255277","_from":"97372","_to":"1125369","book":7,"selection":{"text":"Ἀρήτη, θύγατερ Ῥηξήνορος ἀντιθέοιο,147σόν τε πόσιν σά τε γούναθ’ ἱκάνω πολλὰ μογήσας148τούσδε τε δαιτυμόνας· τοῖσιν θεοὶ ὄλβια δοῖεν149ζωέμεναι, καὶ παισὶν ἐπιτρέψειεν ἕκαστος150κτήματ’ ἐνὶ μεγάροισι γέρας θ’ ὅ τι δῆμος ἔδωκεν·151αὐτὰρ ἐμοὶ πομπὴν ὀτρύνετε πατρίδ’ ἱκέσθαι152θᾶσσον, ἐπεὶ δὴ δηθὰ φίλων ἄπο πήματα πάσχω."},"type":"INR.VERBAL-NEAR"},{"_id":"1264284","_from":"97372","_to":"99653","book":7,"selection":{"text":"Καλυψὼ255ναίει ἐυπλόκαμος"},"type":"COG.FAR"},{"_id":"1264162","_from":"97372","_to":"99653","book":7,"selection":{"text":"ἐς Ὠγυγίην πέλασαν θεοί, ἔνθα Καλυψὼ255ναίει ἐυπλόκαμος"},"type":"INR.NONVERBAL-NEAR/UND"},{"_id":"1260799","_from":"1123744","_to":"1122948","book":7,"selection":{"text":"Κύκλωπές"},"type":"COG.FAR"},{"_id":"1254289","_from":"645196","_to":"1128411","book":7,"selection":{"text":"ἠλάκατα στρωφῶσιν"},"type":"INR.NONVERBAL-NEAR"},{"_id":"1259811","_from":"1123744","_to":"97372","book":7,"selection":{"text":"μιν"},"type":"INR.VERBAL-NEAR/UND"},{"_id":"1256583","_from":"641429","_to":"94990","book":7,"selection":{"text":"σῖτον δ’ αἰδοίη ταμίη παρέθηκε φέρουσα"},"type":"INR.NONVERBAL-NEAR"},{"_id":"1248504","_from":"97372","_to":"1123744","book":7,"selection":{"text":"Ἀλκινόου"},"type":"COG.FAR"},{"_id":"1259884","_from":"1123744","_to":"99765","book":7,"selection":{"text":"ἀθανάτων"},"type":"COG.FAR"},{"_id":"1264087","_from":"100295","_to":"98206","book":7,"selection":{"text":"Ζεὺς ἔλσας ἐκέασσε μέσῳ ἐνὶ οἴνοπι πόντῳ.251ἔνθ’ ἄλλοι μὲν πάντες ἀπέφθιθεν ἐσθλοὶ ἑταῖροι,"},"type":"INR.NONVERBAL-FAR"},{"_id":"1267977","_from":"1125369","_to":"1123744","book":7,"selection":{"text":"πὰρ δὲ γυνὴ δέσποινα λέχος πόρσυνε"},"type":"INR.NONVERBAL-NEAR/UND"},{"_id":"1267468","_from":"1123744","_to":"975898","book":7,"selection":{"text":"λαῶν ἡμετέρων"},"type":"COG.FAR"},{"_id":"1250731","_from":"97372","_to":"976135","book":7,"selection":{"text":"τοι ἔπειτα φίλους"},"type":"COG.FAR"},{"_id":"1253357","_from":"97372","_to":"1123744","book":7,"selection":{"text":"αὐτὰρ Ὀδυσσεὺς82Ἀλκινόου πρὸς δώματ’ ἴε κλυτά"},"type":"INR.NONVERBAL-NEAR/UND"},{"_id":"1247428","_from":"101630","_to":"97372","book":7,"selection":{"text":"ἔνθα οἱ ἀντεβόλησε θεά, γλαυκῶπις Ἀθήνη,"},"type":"INR.NONVERBAL-NEAR/UND"},{"_id":"1248449","_from":"97372","_to":"101630","book":7,"selection":{"text":"ὦ τέκος, οὐκ ἄν μοι δόμον ἀνέρος ἡγήσαιο23Ἀλκινόου, ὃς τοῖσδε μετ’ ἀνθρώποισι ἀνάσσει;24καὶ γὰρ ἐγὼ ξεῖνος ταλαπείριος ἐνθάδ’ ἱκάνω25τηλόθεν ἐξ ἀπίης γαίης· τῷ οὔ τινα οἶδα26ἀνθρώπων, οἳ τήνδε πόλιν καὶ γαῖαν ἔχουσιν."},"type":"INR.VERBAL-NEAR"},{"_id":"1250393","_from":"1250358","_to":"1125369","book":7,"selection":{"text":"ἔκ τε φίλων παίδων"},"type":"COG.NEAR"},{"_id":"1256155","_from":"1123744","_to":"97372","book":7,"selection":{"text":"χειρὸς ἑλὼν Ὀδυσῆα δαΐφρονα ποικιλομήτην"},"type":"INR.NONVERBAL-NEAR"},{"_id":"1267728","_from":"97372","_to":"100295","book":7,"selection":{"text":"Ζεῦ πάτερ, αἴθ’ ὅσα εἶπε τελευτήσειεν ἅπαντα332Ἀλκίνοος· τοῦ μέν κεν ἐπὶ ζείδωρον ἄρουραν333ἄσβεστον κλέος εἴη, ἐγὼ δέ κε πατρίδ’ ἱκοίμην."},"type":"INR.VERBAL-FAR"},{"_id":"1266244","_from":"1123744","_to":"109201","book":7,"selection":{"text":"ἀμφιπόλοισι γυναιξὶν"},"type":"COG.FAR"},{"_id":"1267106","_from":"1123744","_to":"101630","book":7,"selection":{"text":"Ἀθηναίη"},"type":"COG.FAR"},{"_id":"1249165","_from":"101630","_to":"97372","book":7,"selection":{"text":"οὗτος δή τοι, ξεῖνε πάτερ, δόμος, ὅν με κελεύεις49πεφραδέμεν· δήεις δὲ διοτρεφέας βασιλῆας50δαίτην δαινυμένους· σὺ δ’ ἔσω κίε,  μηδέ τι θυμῷ51τάρβει· θαρσαλέος γὰρ ἀνὴρ ἐν πᾶσιν ἀμείνων52ἔργοισιν τελέθει, εἰ καί ποθεν ἄλλοθεν ἔλθοι.53δέσποιναν μὲν πρῶτα κιχήσεαι ἐν μεγάροισιν·54Ἀρήτη δ’ ὄνομ’ ἐστὶν ἐπώνυμον, ἐκ δὲ τοκήων55τῶν αὐτῶν οἵ περ τέκον Ἀλκίνοον βασιλῆα.56Ναυσίθοον μὲν πρῶτα Ποσειδάων ἐνοσίχθων57γείνατο καὶ Περίβοια, γυναικῶν εἶδος ἀρίστη,58ὁπλοτάτη θυγάτηρ μεγαλήτορος Εὐρυμέδοντος,59ὅς ποθ’ ὑπερθύμοισι Γιγάντεσσιν βασίλευεν.60ἀλλ’ ὁ μὲν ὤλεσε λαὸν ἀτάσθαλον,  ὤλετο δ’ αὐτός·61τῇ δὲ Ποσειδάων ἐμίγη καὶ ἐγείνατο παῖδα62Ναυσίθοον μεγάθυμον, ὃς ἐν Φαίηξιν ἄνασσε·63Ναυσίθοος δ’ ἔτεκεν Ῥηξήνορά τ’ Ἀλκίνοόν τε.64τὸν μὲν ἄκουρον ἐόντα βάλ’ ἀργυρότοξος Ἀπόλλων65νυμφίον ἐν μεγάρῳ,  μίαν οἴην παῖδα λιπόντα66Ἀρήτην· τὴν δ’ Ἀλκίνοος ποιήσατ’ ἄκοιτιν,67καί μιν ἔτις’, ὡς οὔ τις ἐπὶ χθονὶ τίεται ἄλλη,68ὅσσαι νῦν γε γυναῖκες ὑπ’ ἀνδράσιν οἶκον ἔχουσιν.69ὣς κείνη περὶ κῆρι τετίμηταί τε καὶ ἔστιν70ἔκ τε φίλων παίδων ἔκ τ’ αὐτοῦ Ἀλκινόοιο71καὶ λαῶν, οἵ μίν ῥα θεὸν ὣς εἰσορόωντες72δειδέχαται μύθοισιν, ὅτε στείχῃς’ ἀνὰ ἄστυ.73οὐ μὲν γάρ τι νόου γε καὶ αὐτὴ δεύεται ἐσθλοῦ·74ᾗσι τ’ ἐὺ φρονέῃσι καὶ ἀνδράσι νείκεα λύει.75εἴ κέν τοι κείνη γε φίλα φρονέῃς’ ἐνὶ θυμῷ,76ἐλπωρή τοι ἔπειτα φίλους τ’ ἰδέειν καὶ ἱκέσθαι77οἶκον ἐς ὑψόροφον καὶ σὴν ἐς πατρίδα γαῖαν."},"type":"INR.VERBAL-NEAR"},{"_id":"1260164","_from":"99765","_to":"975898","book":7,"selection":{"text":"τὸ πάρος γε θεοὶ φαίνονται ἐναργεῖς202ἡμῖν"},"type":"INR.NONVERBAL-NEAR/UND"},{"_id":"1267153","_from":"1123744","_to":"1124092","book":7,"selection":{"text":"παῖδά τ’ ἐμὴν"},"type":"COG.FAR"},{"_id":"1249697","_from":"101630","_to":"1249681","book":7,"selection":{"text":"ὑπερθύμοισι Γιγάντεσσιν"},"type":"COG.FAR"},{"_id":"1255719","_from":"1255685","_to":"1123744","book":7,"selection":{"text":"Ἀλκίνο’, οὐ μέν τοι τόδε κάλλιον, οὐδὲ ἔοικε,160ξεῖνον μὲν χαμαὶ ἧσθαι ἐπ’ ἐσχάρῃ ἐν κονίῃσιν,161οἵδε δὲ σὸν μῦθον ποτιδέγμενοι ἰσχανόωνται.162ἄλλ’ ἄγε δὴ ξεῖνον μὲν ἐπὶ θρόνου ἀργυροήλου163εἷσον ἀναστήσας, σὺ δὲ κηρύκεσσι κέλευσον164οἶνον ἐπικρῆσαι, ἵνα καὶ Διὶ τερπικεραύνῳ165σπείσομεν,  ὅς θ’ ἱκέτῃσιν ἅμ’ αἰδοίοισιν ὀπηδεῖ·166δόρπον δὲ ξείνῳ ταμίη δότω ἔνδον ἐόντων."},"type":"INR.VERBAL-NEAR"},{"_id":"1266114","_from":"1124092","_to":"97372","book":7,"selection":{"text":"αἴθοπα οἶνον"},"type":"INR.NONVERBAL-NEAR"},{"_id":"1261459","_from":"97372","_to":"99765","book":7,"selection":{"text":"ἀθανάτοισιν"},"type":"COG.FAR"},{"_id":"1246145","_from":"1246129","_to":"1124092","book":7,"selection":{"text":"δαῖε δέ οἱ πῦρ8γρῆυς Ἀπειραίη"},"type":"INR.NONVERBAL-NEAR"},{"_id":"1255587","_from":"97372","_to":"976135","book":7,"selection":{"text":"φίλων"},"type":"COG.FAR"},{"_id":"1250107","_from":"1123044","_to":"1123744","book":7,"selection":{"text":"Ναυσίθοος δ’ ἔτεκεν Ῥηξήνορά τ’ Ἀλκίνοόν τε."},"type":"INR.NONVERBAL-NEAR"},{"_id":"1265792","_from":"97372","_to":"1124092","book":7,"selection":{"text":"θυγατρὸς"},"type":"COG.FAR"},{"_id":"1266151","_from":"1124092","_to":"97372","book":7,"selection":{"text":"μοι τάδε εἵματ’ ἔδωκε."},"type":"INR.NONVERBAL-NEAR"},{"_id":"1266299","_from":"97372","_to":"1123744","book":7,"selection":{"text":"ἥρως, μή τοι τοὔνεκ’ ἀμύμονα νείκεε κούρην·304ἡ μὲν γάρ μ’ ἐκέλευε σὺν ἀμφιπόλοισιν ἕπεσθαι,305ἀλλ’ ἐγὼ οὐκ ἔθελον δείσας αἰσχυνόμενός τε,306μή πως καὶ σοὶ θυμὸς ἐπισκύσσαιτο ἰδόντι·307δύσζηλοι γάρ τ’ εἰμὲν ἐπὶ χθονὶ φῦλ’ ἀνθρώπων."},"type":"INR.VERBAL-NEAR"},{"_id":"1258893","_from":"1256633","_to":"1128411","book":7,"selection":{"text":"νώμησεν δ’ ἄρα πᾶσιν ἐπαρξάμενος δεπάεσσιν"},"type":"INR.NONVERBAL-NEAR"},{"_id":"1254343","_from":"645196","_to":"1128411","book":7,"selection":{"text":"ἠλάκατα στρωφῶσιν106ἥμεναι"},"type":"INR.NONVERBAL-NEAR"},{"_id":"1253511","_from":"878145","_to":"1123744","book":7,"selection":{"text":"οὓς Ἥφαιστος ἔτευξεν ἰδυίῃσι πραπίδεσσι93δῶμα φυλασσέμεναι μεγαλήτορος Ἀλκινόοιο,"},"type":"INR.NONVERBAL-NEAR"},{"_id":"1250535","_from":"975898","_to":"1125369","book":7,"selection":{"text":"ἔκ τε φίλων παίδων ἔκ τ’ αὐτοῦ Ἀλκινόοιο71καὶ λαῶν"},"type":"COG.FAR"},{"_id":"1262102","_from":"1125369","_to":"97372","book":7,"selection":{"text":"πὰρ δέ οἱ Ἀρήτη"},"type":"INR.NONVERBAL-NEAR/UND"},{"_id":"1254993","_from":"97372","_to":"1128411","book":7,"selection":{"text":"εὗρε δὲ Φαιήκων ἡγήτορας ἠδὲ μέδοντας"},"type":"INR.NONVERBAL-NEAR/UND"},{"_id":"1256308","_from":"1123744","_to":"1256255","book":7,"selection":{"text":"μάλιστα δέ μιν φιλέεσκεν."},"type":"COG.NEAR"},{"_id":"1264256","_from":"99765","_to":"97372","book":7,"selection":{"text":"ἐς Ὠγυγίην πέλασαν θεοί"},"type":"INR.NONVERBAL-FAR"},{"_id":"1266104","_from":"1124092","_to":"97372","book":7,"selection":{"text":"ἥ μοι σῖτον ἔδωκεν ἅλις"},"type":"INR.NONVERBAL-NEAR"},{"_id":"1250591","_from":"975898","_to":"1125369","book":7,"selection":{"text":"δειδέχαται μύθοισιν, ὅτε στείχῃς’ ἀνὰ ἄστυ."},"type":"INR.VERBAL-NEAR"},{"_id":"1255185","_from":"97372","_to":"1123744","book":7,"selection":{"text":"ὄφρ’ ἵκετ’ Ἀρήτην τε καὶ Ἀλκίνοον βασιλῆα."},"type":"INR.NONVERBAL-NEAR/UND"}]